disputable_values_monitor/__init__.py
disputable_values_monitor/cli.py
disputable_values_monitor/config.py
disputable_values_monitor/data.py
disputable_values_monitor/discord.py
disputable_values_monitor/disputer.py
disputable_values_monitor/utils.py
disputable_values_monitor-2.0.5.dist-info/METADATA
disputable_values_monitor-2.0.5.dist-info/WHEEL
disputable_values_monitor-2.0.5.dist-info/entry_points.txt
disputable_values_monitor-2.0.5.dist-info/RECORD
